{
    "local": {
        "09007": 0,
        "09020": 0,
        "10002": 0,
        "10004": 0,
        "10005": 0,
        "10007": 10,
        "10008": 0,
        "10009": 0,
        "10010": 1,
        "10013": 76,
        "10014": 1,
        "10015": 0,
        "10016": 0,
        "10017": 0,
        "10018": 0,
        "10020": 0,
        "63000": 0,
        "64000": 748,
        "65000": 1,
        "66000": 0,
        "67000": 10,
        "68000": 1
    },
    "import": {
        "09007": 0,
        "09020": 2,
        "10002": 2,
        "10004": 7,
        "10005": 5,
        "10007": 13,
        "10008": 3,
        "10009": 4,
        "10010": 2,
        "10013": 5,
        "10014": 0,
        "10015": 3,
        "10016": 1,
        "10017": 4,
        "10018": 2,
        "10020": 0,
        "63000": 30,
        "64000": 25,
        "65000": 30,
        "66000": 24,
        "67000": 8,
        "68000": 34
    }
}